harperdb_cloud/__init__.py
harperdb_cloud/__main__.py
harperdb_cloud/__version__.py
harperdb_cloud/harperdb_cloud.py
harperdb_cloud/libs/__init__.py
harperdb_cloud/libs/browser.py
HarperDBCloud_Python_SDK-2020.6.15.4.dist-info/METADATA
HarperDBCloud_Python_SDK-2020.6.15.4.dist-info/WHEEL
HarperDBCloud_Python_SDK-2020.6.15.4.dist-info/top_level.txt
HarperDBCloud_Python_SDK-2020.6.15.4.dist-info/RECORD
