Metadata-Version: 2.1
Name: HarperDBCloud-Python-SDK
Version: 2020.6.15.4
Summary: HarperDB Cloud Python SDK.
Home-page: https://github.com/Xonshiz/HarperDBCloud-Python
Author: Xonshiz
Author-email: xonshiz@gmail.com
License: UNKNOWN
Keywords: HarperDB Cloud SDK
Platform: UNKNOWN
Classifier: Programming Language :: Python :: 3
Classifier: License :: OSI Approved :: MIT License
Classifier: Operating System :: OS Independent
Requires-Python: >=3
